libpointing/__init__.py
libpointing/libpointing.cp312-win_amd64.pyd
libpointing/libpointing.cpython-312-darwin.so
libpointing/libpointing.cpython-312-x86_64-linux-gnu.so
libpointing-1.1.1.dist-info/METADATA
libpointing-1.1.1.dist-info/WHEEL
libpointing-1.1.1.dist-info/top_level.txt
libpointing-1.1.1.dist-info/RECORD
