Metadata-Version: 2.1
Name: libpointing
Version: 1.1.1
Summary: Python binding for libpointing.
Author: Izzatbek Mukhanov
Author-email: Nicolas Roussel <nicolas.roussel@inria.fr>, Géry Casiez <gery.casiez@univ-lille.fr>
Maintainer-email: Géry Casiez <gery.casiez@univ-lille.fr>
License: GPLv2
Project-URL: homepage, https://libpointing.org
Keywords: mouse,hid,pointing,input,device,transfer function,subpixel,raw-input
Classifier: Programming Language :: Python :: 3
Classifier: License :: OSI Approved :: MIT License
Classifier: Operating System :: OS Independent
Classifier: License :: OSI Approved :: GNU General Public License v2 (GPLv2)
Requires-Python: ==3.12.*
